lifeActuary/__init__.py
lifeActuary/annuities.py
lifeActuary/annuities_certain.py
lifeActuary/commutation_table.py
lifeActuary/commutation_table_frac.py
lifeActuary/life_2heads.py
lifeActuary/mortality_insurance.py
lifeActuary/mortality_table.py
lifeActuary/mortality_table_2heads.py
soa_tables/__init__.py
soa_tables/read_soa_table_xml.py
lifeActuary-1.3.2.dist-info/LICENSE
lifeActuary-1.3.2.dist-info/METADATA
lifeActuary-1.3.2.dist-info/WHEEL
lifeActuary-1.3.2.dist-info/top_level.txt
lifeActuary-1.3.2.dist-info/RECORD
