Metadata-Version: 2.1
Name: lifeActuary
Version: 1.3.2
Summary: A set of actuarial tools for the life actuary
Author-email: Pedro Corte Real <parcr@fct.unl.pt>, "Gracinda R. Guerreiro" <grg@fct.unl.pt>
Maintainer-email: Pedro Corte Real <parcr@fct.unl.pt>, "Gracinda R. Guerreiro" <grg@fct.unl.pt>
License: Copyright (c) 2023 Pedro Corte Real, Gracinda R. Guerreiro
Project-URL: Homepage, https://github.com/parcr/lifeactuary_1.3
Project-URL: Bug Tracker, https://github.com/parcr/lifeactuary_1.3/issues
Classifier: Programming Language :: Python :: 3
Classifier: License :: OSI Approved :: MIT License
Classifier: Operating System :: OS Independent
Requires-Python: >=3.7
License-File: LICENSE
